sapota-0.1.2.dist-info/METADATA
sapota-0.1.2.dist-info/WHEEL
sapota/__init__.py
sapota/sapota.cp311-win_amd64.pyd
sapota-0.1.2.dist-info/RECORD
